<profile>

<ReportVersion>
<Version>2022.1</Version>
</ReportVersion>

<UserAssignments>
<unit>ns</unit>
<ProductFamily>zynquplus</ProductFamily>
<Part>xck26-sfvc784-2LV-c</Part>
<TopModelName>DepthwiseConv2dFinal_4_1_12_4_Pipeline_VITIS_LOOP_117_4</TopModelName>
<TargetClockPeriod>10.00</TargetClockPeriod>
<ClockUncertainty>2.70</ClockUncertainty>
<FlowTarget>vivado</FlowTarget>
</UserAssignments>

<PerformanceEstimates>
<PipelineType>no</PipelineType>
<SummaryOfTimingAnalysis>
<unit>ns</unit>
<EstimatedClockPeriod>7.016</EstimatedClockPeriod>
</SummaryOfTimingAnalysis>
<SummaryOfOverallLatency>
<unit>clock cycles</unit>
<Best-caseLatency>162</Best-caseLatency>
<Average-caseLatency>162</Average-caseLatency>
<Worst-caseLatency>162</Worst-caseLatency>
<Best-caseRealTimeLatency>1.620 us</Best-caseRealTimeLatency>
<Average-caseRealTimeLatency>1.620 us</Average-caseRealTimeLatency>
<Worst-caseRealTimeLatency>1.620 us</Worst-caseRealTimeLatency>
<Interval-min>162</Interval-min>
<Interval-max>162</Interval-max>
</SummaryOfOverallLatency>
<SummaryOfLoopLatency>
<VITIS_LOOP_117_4>
<TripCount>12</TripCount>
<Latency>160</Latency>
<AbsoluteTimeLatency>1600</AbsoluteTimeLatency>
<PipelineII>8</PipelineII>
<PipelineDepth>73</PipelineDepth>
<InstanceList>
</InstanceList>
</VITIS_LOOP_117_4>
</SummaryOfLoopLatency>
</PerformanceEstimates>

<AreaEstimates>
<Resources>
<DSP>10</DSP>
<FF>3282</FF>
<LUT>2075</LUT>
<BRAM_18K>0</BRAM_18K>
<URAM>0</URAM>
</Resources>
<AvailableResources>
<BRAM_18K>288</BRAM_18K>
<DSP>1248</DSP>
<FF>234240</FF>
<LUT>117120</LUT>
<URAM>64</URAM>
</AvailableResources>
</AreaEstimates>

<InterfaceSummary>
<RtlPorts>
<name>ap_clk</name>
<Object>DepthwiseConv2dFinal&lt;4, 1, 12, 4&gt;_Pipeline_VITIS_LOOP_117_4</Object>
<Type>return value</Type>
<Scope></Scope>
<IOProtocol>ap_ctrl_hs</IOProtocol>
<IOConfig></IOConfig>
<Dir>in</Dir>
<Bits>1</Bits>
<Attribute>control</Attribute>
</RtlPorts>
<RtlPorts>
<name>ap_rst</name>
<Object>DepthwiseConv2dFinal&lt;4, 1, 12, 4&gt;_Pipeline_VITIS_LOOP_117_4</Object>
<Type>return value</Type>
<Scope></Scope>
<IOProtocol>ap_ctrl_hs</IOProtocol>
<IOConfig></IOConfig>
<Dir>in</Dir>
<Bits>1</Bits>
<Attribute>control</Attribute>
</RtlPorts>
<RtlPorts>
<name>ap_start</name>
<Object>DepthwiseConv2dFinal&lt;4, 1, 12, 4&gt;_Pipeline_VITIS_LOOP_117_4</Object>
<Type>return value</Type>
<Scope></Scope>
<IOProtocol>ap_ctrl_hs</IOProtocol>
<IOConfig></IOConfig>
<Dir>in</Dir>
<Bits>1</Bits>
<Attribute>control</Attribute>
</RtlPorts>
<RtlPorts>
<name>ap_done</name>
<Object>DepthwiseConv2dFinal&lt;4, 1, 12, 4&gt;_Pipeline_VITIS_LOOP_117_4</Object>
<Type>return value</Type>
<Scope></Scope>
<IOProtocol>ap_ctrl_hs</IOProtocol>
<IOConfig></IOConfig>
<Dir>out</Dir>
<Bits>1</Bits>
<Attribute>control</Attribute>
</RtlPorts>
<RtlPorts>
<name>ap_idle</name>
<Object>DepthwiseConv2dFinal&lt;4, 1, 12, 4&gt;_Pipeline_VITIS_LOOP_117_4</Object>
<Type>return value</Type>
<Scope></Scope>
<IOProtocol>ap_ctrl_hs</IOProtocol>
<IOConfig></IOConfig>
<Dir>out</Dir>
<Bits>1</Bits>
<Attribute>control</Attribute>
</RtlPorts>
<RtlPorts>
<name>ap_ready</name>
<Object>DepthwiseConv2dFinal&lt;4, 1, 12, 4&gt;_Pipeline_VITIS_LOOP_117_4</Object>
<Type>return value</Type>
<Scope></Scope>
<IOProtocol>ap_ctrl_hs</IOProtocol>
<IOConfig></IOConfig>
<Dir>out</Dir>
<Bits>1</Bits>
<Attribute>control</Attribute>
</RtlPorts>
<RtlPorts>
<name>input_buf_address0</name>
<Object>input_buf</Object>
<Type>array</Type>
<Scope></Scope>
<IOProtocol>ap_memory</IOProtocol>
<IOConfig></IOConfig>
<Dir>out</Dir>
<Bits>6</Bits>
<Attribute>address</Attribute>
</RtlPorts>
<RtlPorts>
<name>input_buf_ce0</name>
<Object>input_buf</Object>
<Type>array</Type>
<Scope></Scope>
<IOProtocol>ap_memory</IOProtocol>
<IOConfig></IOConfig>
<Dir>out</Dir>
<Bits>1</Bits>
<Attribute>control</Attribute>
</RtlPorts>
<RtlPorts>
<name>input_buf_q0</name>
<Object>input_buf</Object>
<Type>array</Type>
<Scope></Scope>
<IOProtocol>ap_memory</IOProtocol>
<IOConfig></IOConfig>
<Dir>in</Dir>
<Bits>32</Bits>
<Attribute>data</Attribute>
</RtlPorts>
<RtlPorts>
<name>input_buf_1_address0</name>
<Object>input_buf_1</Object>
<Type>array</Type>
<Scope></Scope>
<IOProtocol>ap_memory</IOProtocol>
<IOConfig></IOConfig>
<Dir>out</Dir>
<Bits>6</Bits>
<Attribute>address</Attribute>
</RtlPorts>
<RtlPorts>
<name>input_buf_1_ce0</name>
<Object>input_buf_1</Object>
<Type>array</Type>
<Scope></Scope>
<IOProtocol>ap_memory</IOProtocol>
<IOConfig></IOConfig>
<Dir>out</Dir>
<Bits>1</Bits>
<Attribute>control</Attribute>
</RtlPorts>
<RtlPorts>
<name>input_buf_1_q0</name>
<Object>input_buf_1</Object>
<Type>array</Type>
<Scope></Scope>
<IOProtocol>ap_memory</IOProtocol>
<IOConfig></IOConfig>
<Dir>in</Dir>
<Bits>32</Bits>
<Attribute>data</Attribute>
</RtlPorts>
<RtlPorts>
<name>input_buf_2_address0</name>
<Object>input_buf_2</Object>
<Type>array</Type>
<Scope></Scope>
<IOProtocol>ap_memory</IOProtocol>
<IOConfig></IOConfig>
<Dir>out</Dir>
<Bits>6</Bits>
<Attribute>address</Attribute>
</RtlPorts>
<RtlPorts>
<name>input_buf_2_ce0</name>
<Object>input_buf_2</Object>
<Type>array</Type>
<Scope></Scope>
<IOProtocol>ap_memory</IOProtocol>
<IOConfig></IOConfig>
<Dir>out</Dir>
<Bits>1</Bits>
<Attribute>control</Attribute>
</RtlPorts>
<RtlPorts>
<name>input_buf_2_q0</name>
<Object>input_buf_2</Object>
<Type>array</Type>
<Scope></Scope>
<IOProtocol>ap_memory</IOProtocol>
<IOConfig></IOConfig>
<Dir>in</Dir>
<Bits>32</Bits>
<Attribute>data</Attribute>
</RtlPorts>
<RtlPorts>
<name>input_buf_3_address0</name>
<Object>input_buf_3</Object>
<Type>array</Type>
<Scope></Scope>
<IOProtocol>ap_memory</IOProtocol>
<IOConfig></IOConfig>
<Dir>out</Dir>
<Bits>6</Bits>
<Attribute>address</Attribute>
</RtlPorts>
<RtlPorts>
<name>input_buf_3_ce0</name>
<Object>input_buf_3</Object>
<Type>array</Type>
<Scope></Scope>
<IOProtocol>ap_memory</IOProtocol>
<IOConfig></IOConfig>
<Dir>out</Dir>
<Bits>1</Bits>
<Attribute>control</Attribute>
</RtlPorts>
<RtlPorts>
<name>input_buf_3_q0</name>
<Object>input_buf_3</Object>
<Type>array</Type>
<Scope></Scope>
<IOProtocol>ap_memory</IOProtocol>
<IOConfig></IOConfig>
<Dir>in</Dir>
<Bits>32</Bits>
<Attribute>data</Attribute>
</RtlPorts>
<RtlPorts>
<name>weights_address0</name>
<Object>weights</Object>
<Type>array</Type>
<Scope></Scope>
<IOProtocol>ap_memory</IOProtocol>
<IOConfig></IOConfig>
<Dir>out</Dir>
<Bits>8</Bits>
<Attribute>address</Attribute>
</RtlPorts>
<RtlPorts>
<name>weights_ce0</name>
<Object>weights</Object>
<Type>array</Type>
<Scope></Scope>
<IOProtocol>ap_memory</IOProtocol>
<IOConfig></IOConfig>
<Dir>out</Dir>
<Bits>1</Bits>
<Attribute>control</Attribute>
</RtlPorts>
<RtlPorts>
<name>weights_q0</name>
<Object>weights</Object>
<Type>array</Type>
<Scope></Scope>
<IOProtocol>ap_memory</IOProtocol>
<IOConfig></IOConfig>
<Dir>in</Dir>
<Bits>32</Bits>
<Attribute>data</Attribute>
</RtlPorts>
<RtlPorts>
<name>weights_address1</name>
<Object>weights</Object>
<Type>array</Type>
<Scope></Scope>
<IOProtocol>ap_memory</IOProtocol>
<IOConfig></IOConfig>
<Dir>out</Dir>
<Bits>8</Bits>
<Attribute>address</Attribute>
</RtlPorts>
<RtlPorts>
<name>weights_ce1</name>
<Object>weights</Object>
<Type>array</Type>
<Scope></Scope>
<IOProtocol>ap_memory</IOProtocol>
<IOConfig></IOConfig>
<Dir>out</Dir>
<Bits>1</Bits>
<Attribute>control</Attribute>
</RtlPorts>
<RtlPorts>
<name>weights_q1</name>
<Object>weights</Object>
<Type>array</Type>
<Scope></Scope>
<IOProtocol>ap_memory</IOProtocol>
<IOConfig></IOConfig>
<Dir>in</Dir>
<Bits>32</Bits>
<Attribute>data</Attribute>
</RtlPorts>
<RtlPorts>
<name>depth3_o79_din</name>
<Object>depth3_o79</Object>
<Type>pointer</Type>
<Scope></Scope>
<IOProtocol>ap_fifo</IOProtocol>
<IOConfig></IOConfig>
<Dir>out</Dir>
<Bits>32</Bits>
<Attribute>control</Attribute>
</RtlPorts>
<RtlPorts>
<name>depth3_o79_num_data_valid</name>
<Object>depth3_o79</Object>
<Type>pointer</Type>
<Scope></Scope>
<IOProtocol>ap_fifo</IOProtocol>
<IOConfig></IOConfig>
<Dir>in</Dir>
<Bits>2</Bits>
<Attribute>control</Attribute>
</RtlPorts>
<RtlPorts>
<name>depth3_o79_fifo_cap</name>
<Object>depth3_o79</Object>
<Type>pointer</Type>
<Scope></Scope>
<IOProtocol>ap_fifo</IOProtocol>
<IOConfig></IOConfig>
<Dir>in</Dir>
<Bits>2</Bits>
<Attribute>unknown</Attribute>
</RtlPorts>
<RtlPorts>
<name>depth3_o79_full_n</name>
<Object>depth3_o79</Object>
<Type>pointer</Type>
<Scope></Scope>
<IOProtocol>ap_fifo</IOProtocol>
<IOConfig></IOConfig>
<Dir>in</Dir>
<Bits>1</Bits>
<Attribute>control</Attribute>
</RtlPorts>
<RtlPorts>
<name>depth3_o79_write</name>
<Object>depth3_o79</Object>
<Type>pointer</Type>
<Scope></Scope>
<IOProtocol>ap_fifo</IOProtocol>
<IOConfig></IOConfig>
<Dir>out</Dir>
<Bits>1</Bits>
<Attribute>control</Attribute>
</RtlPorts>
</InterfaceSummary>

</profile>
